16x8 Dual Port RAM Design with Testcases (Single Clock)/design.sv
// Code your design here

// I'm designing 16x8 dual port ram where data width = 8, depth or number of memory location = 16, and address width =  4 ( as 2^4 = 16 )

module dual_port_ram #(

  parameter data_width = 8,
  parameter addr_width = 4,
  parameter depth = 16

) (

  input clk,
  input rst,

  // for port A
  input [ data_width - 1 : 0] din_a,
  output reg [ data_width - 1 : 0] dout_a,
  input [ addr_width - 1 : 0 ] addr_a,
  input we_a,
  input re_a,

  // for port B
  input [ data_width - 1 : 0] din_b,
  output reg [ data_width - 1 : 0] dout_b,
  input [ addr_width - 1 : 0 ] addr_b,
  input we_b,
  input re_b

);

  // then we have to declare internal memory arrary
  reg [ data_width - 1 : 0 ] mem [ 0 : depth - 1 ];

  // write/read and reset logic
  always @(posedge clk or negedge rst) begin

    integer i;

    if(rst) begin

      
      // For port-A write
      if(we_a) 
        mem[addr_a] <= din_a;
        
      
      
      // For writing input data to only first and last location of ram
      /*if(we_a) begin
        mem[0] <= din_a;
        mem[depth-1] <= din_a;
      end
	*/
      
      
      // For port-A read
      if(re_a)
        dout_a <= mem[addr_a]; // for reading port-A data from Port-A
      
      // dout_a <= mem[addr_b]; // for reading port-B data from port-A

      
      // For port-B write
      if(we_b) 
        mem[addr_b] <= din_b;

      
      // For port-B read
      if(re_b)
        dout_b <= mem[addr_b]; // for reading port-B data from port-B
      
      // dout_b <= mem[addr_a]; // for reading port-A input data from port-B

    end

    else begin

      dout_a <= 1'b0;
      dout_b <= 1'b0;

      for (i=0; i < 16; i = i + 1) begin
        mem[i] <= 0;
      end

    end

  end


endmodule

16x8 Dual Port RAM Design with Testcases (Single Clock)/testbench.sv
// Code your testbench here
// or browse Examples
module tb;

  reg [7:0] din_a, din_b;
  reg [3:0] addr_a, addr_b;
  reg we_a, we_b;
  reg re_a, re_b;
  wire [7:0] dout_a, dout_b;
  reg clk;
  reg rst;

  dual_port_ram dut(

    .clk(clk),
    .rst(rst),
    .din_a(din_a),
    .din_b(din_b),
    .dout_a(dout_a),
    .dout_b(dout_b),
    .addr_a(addr_a),
    .addr_b(addr_b),
    .we_a(we_a),
    .we_b(we_b),
    .re_a(re_a),
    .re_b(re_b)

  );

  integer i;

  // clock generation
  initial begin

    clk = 0;
    forever #5 clk = ~clk;

  end


  // actual testcases
  initial begin

    $dumpfile("test_dpt.vcd");
    $dumpvars(0, tb);

    $monitor("Time = %t | Din_a = %b | Din_b = %b | addr_a = %b | addr_b = %b | we_a = %b | we_b = %b | @addr_a = %b | @addr_b = %b | re_a = %b | re_b = %b | rst = %b | dout_a = %b | dout_b = %b", $realtime, din_a, din_b, addr_a, addr_b, we_a, we_b, dut.mem[addr_a], dut.mem[addr_b], re_a, re_b, rst, dout_a, dout_b);


    // initially
    din_a = 8'b1; din_b = 8'b10;

    addr_a = 4'b1010; addr_b = 4'b1111; // for writing on different addresses

    // addr_a = 4'b1111; addr_b = 4'b1111; // for writing on same address

    we_a = 1'b0; we_b = 1'b0;

    re_a = 1'b0; re_b = 1'b0;

    rst = 1'b1;


    // check data in memory before any write. (Default value) or used this for loop block to check data after reset testcase also.
    /*
    for(i=0; i<16; i=i+1) begin
      $display("data is %0b at %0b", dut.mem[i], i);
    end
    */


    /*
    // WWWWW-RRRRR (Write and Read by Port-A)
    @(posedge clk);

    we_a = 1; re_a = 0;

    for (i = 0; i < 5; i = i + 1) begin
      addr_a = i;
      @(posedge clk);
    end

    we_a = 0; re_a = 1;

    for (i = 0; i < 5; i = i + 1) begin
      addr_a = i;
      @(posedge clk);
      //$display("Read A: addr = %0d, data = %0d", i, dout_a);
    end

    re_a = 0;
	*/


    /*
    // WRWRWRWRWRWR... (through port-B)
    for (i = 5; i < 10; i = i + 1) begin

      addr_b = i;
      we_b = 1; re_b = 0;
      @(posedge clk);
      we_b = 0; re_b = 1;
      @(posedge clk);
      //$display("Read B: addr = %0d, data = %0d", i, dout_b);

    end

    re_b = 0;

*/


    // write data from both ports to different memory locations


    /*    
    @(posedge clk);
    we_a = 1'b1;
    we_b = 1'b1; 
	*/


    /*
    @(posedge clk);
    we_b = 1'b0;
    we_a = 1'b1;

    @(posedge clk);
    we_a = 1'b0;
    we_b = 1'b1;
    */


    /*
     @(posedge clk);
      we_a = 1'b0;
      we_b = 1'b0;
   */  


    // when both ports try to write on same address
    /*
    @(posedge clk);

    we_a = 1;
    we_b = 1;

    @(posedge clk);
    we_a = 0; we_b = 0; 

    @(posedge clk);
    re_a = 1'b1;
    re_b = 1'b1;
    $display("dout_a = %b | dout_b = %b", dout_a, dout_b);
    */



    // read data from memory locations
    /*
    @(posedge clk);
    we_a = 1'b0;
    we_b = 1'b0;
    re_a = 1'b1;
    re_b = 1'b1;
   */


    // check data in memory after write.
    /*for(i=0; i<16; i=i+1) begin
      $display("data is %0b at %0b", dut.mem[i], i);
    end
   */



    // Read during write (different address)
    /*
    addr_a = 4'b0001; din_a = 8'hAA; din_b = 8'h0A; we_a = 1;
    addr_b = 4'b0010; re_b = 1;

    @(posedge clk);

    we_a = 0; re_b = 0;
*/


    // Read during write (same address)
    /*
    addr_a = 4'd3; din_a = 8'hBB; we_a = 1;
    addr_b = 4'd3; re_b = 1;
    @(posedge clk);
    we_a = 0; re_b = 0;
*/


    // Write to all 16 memory address locations using Port A
  
    for (i = 0; i < 16; i = i + 1) begin
      @(posedge clk);
      addr_a = i;
      din_a  = i;
      we_a   = 1;
    end

    @(posedge clk);
    we_a = 0;

    $display("Write completed!");

    // Read from all 16 locations using Port B
    
    for (i = 0; i < 16; i = i + 1) begin
      @(posedge clk);
      addr_b = i;
      re_b   = 1;
    end

    @(posedge clk);
    re_b = 0;

    $display("Read completed!");



    /* use this for check reset at any time ( clears all memory locations and both port's output pins). First write something, then read it, then reset, and then read again.*/

    /*
    #10;
    rst = 1'b0;
    */


    // check final memory data
    #5;
    for(i=0; i<16; i=i+1) begin
      $display("data is %0b at %0b", dut.mem[i], i);
    end



    #10;

    #10; $finish;

  end

endmodule

16x8 Dual Port RAM Design with Testcases (Single Clock)/test_dpt.vcd
$date
	Sun Jun 15 09:46:30 2025
$end

$version
	Synopsys VCS version U-2023.03-SP2_Full64
$end

$timescale
	1ns
$end

$comment Csum: 1 b97dc8fc5e7891b8 $end


$scope module tb $end
$var reg 8 ! din_a [7:0] $end
$var reg 8 " din_b [7:0] $end
$var reg 4 # addr_a [3:0] $end
$var reg 4 $ addr_b [3:0] $end
$var reg 1 % we_a $end
$var reg 1 & we_b $end
$var reg 1 ' re_a $end
$var reg 1 ( re_b $end
$var wire 8 ) dout_a [7:0] $end
$var wire 8 * dout_b [7:0] $end
$var reg 1 + clk $end
$var reg 1 , rst $end
$var integer 32 - i $end

$scope module dut $end
$var wire 1 + clk $end
$var wire 1 , rst $end
$var wire 8 ! din_a [7:0] $end
$var reg 8 ) dout_a [7:0] $end
$var wire 4 # addr_a [3:0] $end
$var wire 1 % we_a $end
$var wire 1 ' re_a $end
$var wire 8 " din_b [7:0] $end
$var reg 8 * dout_b [7:0] $end
$var wire 4 $ addr_b [3:0] $end
$var wire 1 & we_b $end
$var wire 1 ( re_b $end

$scope begin unnamed$$_0 $end
$var integer 32 . i $end
$upscope $end

$upscope $end

$upscope $end

$enddefinitions $end

#0
$dumpvars
0+
0'
0(
1,
0%
0&
b1010 #
b1111 $
b00000001 !
b00000010 "
bxxxxxxxx )
bxxxxxxxx *
b00000000000000000000000000000000 -
bxxxxxxxxxxxxxxxxxxxxxxxxxxxxxxxx .
$end
#5
1+
b0000 #
b00000000 !
1%
b00000000000000000000000000000001 -
#10
0+
#15
1+
b0001 #
b00000001 !
b00000000000000000000000000000010 -
#20
0+
#25
1+
b0010 #
b00000010 !
b00000000000000000000000000000011 -
#30
0+
#35
1+
b0011 #
b00000011 !
b00000000000000000000000000000100 -
#40
0+
#45
1+
b0100 #
b00000100 !
b00000000000000000000000000000101 -
#50
0+
#55
1+
b0101 #
b00000101 !
b00000000000000000000000000000110 -
#60
0+
#65
1+
b0110 #
b00000110 !
b00000000000000000000000000000111 -
#70
0+
#75
1+
b0111 #
b00000111 !
b00000000000000000000000000001000 -
#80
0+
#85
1+
b1000 #
b00001000 !
b00000000000000000000000000001001 -
#90
0+
#95
1+
b1001 #
b00001001 !
b00000000000000000000000000001010 -
#100
0+
#105
1+
b1010 #
b00001010 !
b00000000000000000000000000001011 -
#110
0+
#115
1+
b1011 #
b00001011 !
b00000000000000000000000000001100 -
#120
0+
#125
1+
b1100 #
b00001100 !
b00000000000000000000000000001101 -
#130
0+
#135
1+
b1101 #
b00001101 !
b00000000000000000000000000001110 -
#140
0+
#145
1+
b1110 #
b00001110 !
b00000000000000000000000000001111 -
#150
0+
#155
1+
b1111 #
b00001111 !
b00000000000000000000000000010000 -
#160
0+
#165
1+
0%
b00000000000000000000000000000000 -
#170
0+
#175
1+
b0000 $
1(
b00000000000000000000000000000001 -
b00000000 *
#180
0+
#185
1+
b0001 $
b00000000000000000000000000000010 -
b00000001 *
#190
0+
#195
1+
b0010 $
b00000000000000000000000000000011 -
b00000010 *
#200
0+
#205
1+
b0011 $
b00000000000000000000000000000100 -
b00000011 *
#210
0+
#215
1+
b0100 $
b00000000000000000000000000000101 -
b00000100 *
#220
0+
#225
1+
b0101 $
b00000000000000000000000000000110 -
b00000101 *
#230
0+
#235
1+
b0110 $
b00000000000000000000000000000111 -
b00000110 *
#240
0+
#245
1+
b0111 $
b00000000000000000000000000001000 -
b00000111 *
#250
0+
#255
1+
b1000 $
b00000000000000000000000000001001 -
b00001000 *
#260
0+
#265
1+
b1001 $
b00000000000000000000000000001010 -
b00001001 *
#270
0+
#275
1+
b1010 $
b00000000000000000000000000001011 -
b00001010 *
#280
0+
#285
1+
b1011 $
b00000000000000000000000000001100 -
b00001011 *
#290
0+
#295
1+
b1100 $
b00000000000000000000000000001101 -
b00001100 *
#300
0+
#305
1+
b1101 $
b00000000000000000000000000001110 -
b00001101 *
#310
0+
#315
1+
b1110 $
b00000000000000000000000000001111 -
b00001110 *
#320
0+
#325
1+
b1111 $
b00000000000000000000000000010000 -
b00001111 *
#330
0+
#335
1+
0(
#340
0+
b00000000000000000000000000000000 -
b00000000000000000000000000010000 -
