Mux8x1/design.sv
// Code your design here
module mux_8_1(

  input wire i0,
  input wire i1,
  input wire i2,
  input wire i3,
  input wire i4,
  input wire i5,
  input wire i6,
  input wire i7,
  input wire [2:0] sel,
  output reg y

);

  always @(*) begin

    case (sel)

      3'b000: y = i0;
      3'b001: y = i1;
      3'b010: y = i2;
      3'b011: y = i3;
      3'b100: y = i4;
      3'b101: y = i5;
      3'b110: y = i6;
      3'b111: y = i7;
      default:  y = i0;
    endcase
  end

endmodule

Mux8x1/testbench.sv
// Code your testbench here
// or browse Examples
module mux_8_1_tb;

  reg i0,i1,i2,i3, i4, i5, i6, i7;
  reg [2:0] sel;
  wire y;

  mux_8_1 dut(

    .i0(i0),
    .i1(i1),
    .i2(i2),
    .i3(i3),
    .i4(i4),
    .i5(i5),
    .i6(i6),
    .i7(i7),
    .sel(sel),
    .y(y)

  );

  initial begin

    $monitor("Time=%0t | sel=%b | y=%b", $time, sel, y);

    $dumpfile("test_mux8x1.vcd");
    $dumpvars(0, mux_8_1_tb);

    i0 = 1'b1; i1 = 1'b0; i2 = 1'b1; i3 = 1'b0; i4=1'b0; i5 = 0; i6 = 1; i7 = 0; sel = 3'b000;

    #5 sel = 3'b000;
    #5 sel = 3'b001;
    #5 sel = 3'b010;
    #5 sel = 3'b011;
    #5 sel = 3'b100;
    #5 sel = 3'b101;
    #5 sel = 3'b110;
    #5 sel = 3'b111;
    
    #5 $finish;

  end
endmodule

Mux8x1/test_mux8x1.vcd
$date
	Sun Jun 15 08:58:54 2025
$end

$version
	Synopsys VCS version U-2023.03-SP2_Full64
$end

$timescale
	1ns
$end

$comment Csum: 1 b8cf15a65da9e680 $end


$scope module mux_8_1_tb $end
$var reg 1 ! i0 $end
$var reg 1 " i1 $end
$var reg 1 # i2 $end
$var reg 1 $ i3 $end
$var reg 1 % i4 $end
$var reg 1 & i5 $end
$var reg 1 ' i6 $end
$var reg 1 ( i7 $end
$var reg 3 ) sel [2:0] $end
$var wire 1 * y $end

$scope module dut $end
$var wire 1 ! i0 $end
$var wire 1 " i1 $end
$var wire 1 # i2 $end
$var wire 1 $ i3 $end
$var wire 1 % i4 $end
$var wire 1 & i5 $end
$var wire 1 ' i6 $end
$var wire 1 ( i7 $end
$var wire 3 ) sel [2:0] $end
$var reg 1 * y $end
$upscope $end

$upscope $end

$enddefinitions $end

#0
$dumpvars
1*
1!
0"
1#
0$
0%
0&
1'
0(
b000 )
$end
#10
b001 )
0*
#15
b010 )
1*
#20
b011 )
0*
#25
b100 )
#30
b101 )
#35
b110 )
1*
#40
b111 )
0*
