Bidirectional Buffer with Testbench in Verilog/design.sv
module bi_buf(
	
  inout wire a,
  inout wire b,
  input wire en

);
  
  assign b = en ? a : 1'bz;  
  assign a = ~en ? b : 1'bz; 
  
endmodule

Bidirectional Buffer with Testbench in Verilog/testbench.sv
module bi_buf_tb;

  reg en;
  
  // As we cannot assign values to Inout ports directly, we have to make seperate variables to drive values A and B.

  reg a_drv, b_drv; 
  wire a, b;
  
  assign a = en ? a_drv : 1'bz; // a drive when en = 1, output to b.
  assign b = en ? 1'bz : b_drv; // b drive when en = 0, output to a.
  
  bi_buf dut (
    .a(a),
    .b(b),
    .en(en)
  );

  initial begin
    
    $dumpfile("bi_buf_tb.vcd");
    $dumpvars(0, bi_buf_tb);

    $monitor("Time = %t | en = %b | a = %b | b = %b", $time, en, a, b);

    
    en = 1; a_drv = 1'b1; b_drv = 1'bz; #5;
    a_drv = 1'b0; #5; // reset value to 0 ( not necessory )

    en = 0; a_drv = 1'bz; b_drv = 1'b1; #5;
    b_drv = 1'b0; #5; // reset value to 0 ( not necessory )
    
    en = 1; a_drv = 1'b1; b_drv = 1'bz; #5;
    a_drv = 1'b0; #5;
    
    en = 0; a_drv = 1'bz; b_drv = 1'b0; #5;
    b_drv = 1'b0; #5;
    
    en = 1; a_drv = 1'bz; b_drv = 1'bz; #5;
   // a_drv = 1'b0; #5;
    
    en = 0; a_drv = 1'bz; b_drv = 1'bz; #5;
   // b_drv = 1'b0; #5;
        
    en = 1; a_drv = 1'bx; b_drv = 1'bz; #5;
   // a_drv = 1'b0; #5;
    
    en = 0; a_drv = 1'bz; b_drv = 1'bx; #5;
   // b_drv = 1'b0; #5;

    $finish;
    
  end

endmodule

Bidirectional Buffer with Testbench in Verilog/bi_buf_tb.vcd
$date
	Sat Jun  7 02:44:19 2025
$end

$version
	Synopsys VCS version U-2023.03-SP2_Full64
$end

$timescale
	1ns
$end

$comment Csum: 1 49a2c66937df482a $end


$scope module bi_buf_tb $end
$var reg 1 ! en $end
$var reg 1 " a_drv $end
$var reg 1 # b_drv $end
$var wire 1 $ a $end
$var wire 1 % b $end

$scope module dut $end
$var wire 1 $ a $end
$var wire 1 % b $end
$var wire 1 ! en $end
$upscope $end

$upscope $end

$enddefinitions $end

#0
$dumpvars
1$
1"
1%
z#
1!
$end
#5
0"
0$
0%
#10
0!
z"
1#
1%
1$
#15
0#
0%
0$
#20
1!
1"
z#
1$
1%
#25
0"
0$
0%
#30
0!
z"
0#
#40
1!
z#
z$
z%
#45
0!
#50
1!
x"
x$
x%
#55
0!
z"
x#
