110100 Sequence Detector FSM in Verilog/design.sv
// Code your design here
module seq_det(

	input clk,
  	input rst,
  	input in,
  	output out
  
);
  
  reg [2:0] current_state, next_state;
 
  parameter a = 0,
          b = 1,
          c = 2,
          d = 3,
          e = 4,
          f = 5;
 
  assign out = (current_state == f) ? b : a;  
  
  /*always @(posedge clk or posedge rst) begin
    
    if (rst)
      current_state <= a;
    else
      current_state <= next_state;
  
  end
  */
  
  // we used active low reset because it is less affected by noise and power on glitches. Active low ( 0 ) is more noise immune and reliable at power on than active high ( 1 ). If active high is used, it can float the inputs at unexpected noise or at power on. That's why we used active low reset.
  
  always @(posedge clk or negedge rst) begin
    
    if (!rst)
      current_state <= next_state;
    else
      current_state <= a;
	
  end
  
  always @(current_state or in) begin
    
    case (current_state)
      
      a: next_state = in ? b : a;
      b: next_state = in ? c : a;
      c: next_state = in ? c : d;
      d: next_state = in ? e : a;
      e: next_state = in ? c : f;
      f: next_state = in ? b : a;
      
    endcase
    
  end
  
endmodule

110100 Sequence Detector FSM in Verilog/testbench.sv
// Code your testbench here
// or browse Examples
module tb;
  reg clk, rst, in;
  wire out;

  seq_det dut (
    .clk(clk),
    .rst(rst),
    .in(in),
    .out(out)
  );

  initial begin
    clk = 0;
    forever #5 clk = ~clk;
  end

  initial begin
    
    $dumpfile("test_fsm.vcd");
    $dumpvars(0, tb);
    
    rst = 1; in = 0;
    #12 rst = 0;

    @(posedge clk) in = 1;
    @(posedge clk) in = 1;
    @(posedge clk) in = 0;
    @(posedge clk) in = 1;
    @(posedge clk) in = 0;
    @(posedge clk) in = 0;
    @(posedge clk) in = 0;
    @(posedge clk) in = 0;
    @(posedge clk) in = 1;
    @(posedge clk) in = 1;
    @(posedge clk) in = 0;
    @(posedge clk) in = 1;
    @(posedge clk) in = 0;
    
    //@(posedge clk) rst = 0; // checking reset
    
    @(posedge clk) in = 0;
    @(posedge clk) in = 0;

    @(posedge clk) $finish;
    
  end

  initial begin
    
    $monitor("Time = %0t | in = %b | out = %b | Current State = %0d | Next State = %0d", $time, in, out, dut.current_state, dut.next_state);
    
  end
 
  
endmodule

110100 Sequence Detector FSM in Verilog/test_fsm.vcd
$date
	Sat Jun  7 02:40:33 2025
$end

$version
	Synopsys VCS version U-2023.03-SP2_Full64
$end

$timescale
	1ns
$end

$comment Csum: 1 40f8e4e7d274061d $end


$scope module tb $end
$var reg 1 ! clk $end
$var reg 1 " rst $end
$var reg 1 # in $end
$var wire 1 $ out $end

$scope module dut $end
$var reg 3 % current_state [2:0] $end
$var reg 3 & next_state [2:0] $end
$var wire 1 ! clk $end
$var wire 1 " rst $end
$var wire 1 # in $end
$var wire 1 $ out $end
$upscope $end

$upscope $end

$enddefinitions $end

#0
$dumpvars
0!
0#
1"
x$
bxxx %
bxxx &
$end
#5
1!
b000 %
0$
b000 &
#10
0!
#12
0"
#15
1!
1#
b001 &
#20
0!
#25
1!
b001 %
b010 &
#30
0!
#35
1!
0#
b000 &
b010 %
b011 &
#40
0!
#45
1!
1#
b010 &
b011 %
b100 &
#50
0!
#55
1!
0#
b000 &
b100 %
b101 &
#60
0!
#65
1!
b101 %
1$
b000 &
#70
0!
#75
1!
b000 %
0$
#80
0!
#85
1!
#90
0!
#95
1!
1#
b001 &
#100
0!
#105
1!
b001 %
b010 &
#110
0!
#115
1!
0#
b000 &
b010 %
b011 &
#120
0!
#125
1!
1#
b010 &
b011 %
b100 &
#130
0!
#135
1!
0#
b000 &
b100 %
b101 &
#140
0!
#145
1!
b101 %
1$
b000 &
#150
0!
#155
1!
b000 %
0$
